lib/__init__.py
lib/agent.py
lib/maze.py
Exploring_Mazes-0.1.0.dist-info/LICENSE
Exploring_Mazes-0.1.0.dist-info/METADATA
Exploring_Mazes-0.1.0.dist-info/WHEEL
Exploring_Mazes-0.1.0.dist-info/top_level.txt
Exploring_Mazes-0.1.0.dist-info/RECORD
